StatsWithSahira/StatsWithSahira.py
StatsWithSahira/__init__.py
StatsWithSahira-0.0.7.dist-info/METADATA
StatsWithSahira-0.0.7.dist-info/WHEEL
StatsWithSahira-0.0.7.dist-info/top_level.txt
StatsWithSahira-0.0.7.dist-info/RECORD
